<annotation>
	<folder>JPEGImages</folder>
	<filename>000033.jpg</filename>
	<path>JPEGImages</path>
	<size>
		<width>498</width>
		<height>332</height>
		<depth>3</depth>
	</size>
	<object>
		<name>ship</name>
		<pose>Unspecified</pose>
		<truncated>0</truncated>
		<difficult>0</difficult>
		<bndbox>
			<xmin>122</xmin>
			<ymin>106</ymin>
			<xmax>230</xmax>
			<ymax>127</ymax>
			<bbox_w>108</bbox_w>
			<bbox_h>21</bbox_h>
		</bndbox>
		<rotated_bndbox>
			<rotated_bbox_cx>175</rotated_bbox_cx>
			<rotated_bbox_cy>117</rotated_bbox_cy>
			<rotated_bbox_w>19</rotated_bbox_w>
			<rotated_bbox_h>108</rotated_bbox_h>
			<rotated_bbox_theta>86.36705780029297</rotated_bbox_theta>
			<x1>121</x1>
			<y1>110</y1>
			<x2>229</x2>
			<y2>104</y2>
			<x3>230</x3>
			<y3>123</y3>
			<x4>122</x4>
			<y4>130</y4>
		</rotated_bndbox>
		<segm>
			<point-1>122,119</point-1>
			<point-2>131,111</point-2>
			<point-3>137,110</point-3>
			<point-4>179,108</point-4>
			<point-5>200,106</point-5>
			<point-6>215,110</point-6>
			<point-7>223,109</point-7>
			<point-8>230,114</point-8>
			<point-9>228,121</point-9>
			<point-10>212,123</point-10>
			<point-11>198,125</point-11>
			<point-12>171,127</point-12>
			<point-13>146,127</point-13>
			<point-14>134,127</point-14>
			<point-15>122,121</point-15>
		</segm>
	</object>
</annotation>