<annotation>
	<folder>JPEGImages</folder>
	<filename>000190.jpg</filename>
	<path>JPEGImages</path>
	<size>
		<width>391</width>
		<height>248</height>
		<depth>3</depth>
	</size>
	<object>
		<name>ship</name>
		<pose>Unspecified</pose>
		<truncated>0</truncated>
		<difficult>0</difficult>
		<bndbox>
			<xmin>239</xmin>
			<ymin>19</ymin>
			<xmax>251</xmax>
			<ymax>52</ymax>
			<bbox_w>12</bbox_w>
			<bbox_h>33</bbox_h>
		</bndbox>
		<rotated_bndbox>
			<rotated_bbox_cx>244</rotated_bbox_cx>
			<rotated_bbox_cy>35</rotated_bbox_cy>
			<rotated_bbox_w>33</rotated_bbox_w>
			<rotated_bbox_h>10</rotated_bbox_h>
			<rotated_bbox_theta>80.53767395019531</rotated_bbox_theta>
			<x1>236</x1>
			<y1>20</y1>
			<x2>247</x2>
			<y2>18</y2>
			<x3>252</x3>
			<y3>51</y3>
			<x4>242</x4>
			<y4>52</y4>
		</rotated_bndbox>
		<segm>
			<point-1>248,52</point-1>
			<point-2>249,44</point-2>
			<point-3>251,40</point-3>
			<point-4>249,36</point-4>
			<point-5>246,30</point-5>
			<point-6>245,24</point-6>
			<point-7>243,19</point-7>
			<point-8>239,20</point-8>
			<point-9>240,26</point-9>
			<point-10>240,34</point-10>
			<point-11>240,40</point-11>
			<point-12>241,46</point-12>
			<point-13>243,50</point-13>
		</segm>
	</object>
	<object>
		<name>ship</name>
		<pose>Unspecified</pose>
		<truncated>0</truncated>
		<difficult>0</difficult>
		<bndbox>
			<xmin>359</xmin>
			<ymin>176</ymin>
			<xmax>377</xmax>
			<ymax>221</ymax>
			<bbox_w>18</bbox_w>
			<bbox_h>45</bbox_h>
		</bndbox>
		<rotated_bndbox>
			<rotated_bbox_cx>367</rotated_bbox_cx>
			<rotated_bbox_cy>198</rotated_bbox_cy>
			<rotated_bbox_w>46</rotated_bbox_w>
			<rotated_bbox_h>11</rotated_bbox_h>
			<rotated_bbox_theta>72.18110656738281</rotated_bbox_theta>
			<x1>354</x1>
			<y1>178</y1>
			<x2>365</x2>
			<y2>175</y2>
			<x3>379</x3>
			<y3>219</y3>
			<x4>368</x4>
			<y4>222</y4>
		</rotated_bndbox>
		<segm>
			<point-1>374,221</point-1>
			<point-2>377,215</point-2>
			<point-3>376,207</point-3>
			<point-4>372,199</point-4>
			<point-5>370,193</point-5>
			<point-6>369,187</point-6>
			<point-7>367,179</point-7>
			<point-8>363,176</point-8>
			<point-9>359,178</point-9>
			<point-10>361,186</point-10>
			<point-11>361,193</point-11>
			<point-12>363,199</point-12>
			<point-13>363,205</point-13>
			<point-14>365,209</point-14>
			<point-15>368,216</point-15>
		</segm>
	</object>
	<object>
		<name>ship</name>
		<pose>Unspecified</pose>
		<truncated>0</truncated>
		<difficult>0</difficult>
		<bndbox>
			<xmin>130</xmin>
			<ymin>132</ymin>
			<xmax>148</xmax>
			<ymax>177</ymax>
			<bbox_w>18</bbox_w>
			<bbox_h>45</bbox_h>
		</bndbox>
		<rotated_bndbox>
			<rotated_bbox_cx>138</rotated_bbox_cx>
			<rotated_bbox_cy>154</rotated_bbox_cy>
			<rotated_bbox_w>47</rotated_bbox_w>
			<rotated_bbox_h>13</rotated_bbox_h>
			<rotated_bbox_theta>74.05460357666016</rotated_bbox_theta>
			<x1>125</x1>
			<y1>133</y1>
			<x2>138</x2>
			<y2>129</y2>
			<x3>151</x3>
			<y3>175</y3>
			<x4>138</x4>
			<y4>178</y4>
		</rotated_bndbox>
		<segm>
			<point-1>145,177</point-1>
			<point-2>148,172</point-2>
			<point-3>148,164</point-3>
			<point-4>146,157</point-4>
			<point-5>142,151</point-5>
			<point-6>138,146</point-6>
			<point-7>138,141</point-7>
			<point-8>135,133</point-8>
			<point-9>131,132</point-9>
			<point-10>132,138</point-10>
			<point-11>130,147</point-11>
			<point-12>133,156</point-12>
			<point-13>134,163</point-13>
			<point-14>138,170</point-14>
			<point-15>140,175</point-15>
		</segm>
	</object>
	<object>
		<name>ship</name>
		<pose>Unspecified</pose>
		<truncated>0</truncated>
		<difficult>0</difficult>
		<bndbox>
			<xmin>206</xmin>
			<ymin>153</ymin>
			<xmax>220</xmax>
			<ymax>197</ymax>
			<bbox_w>14</bbox_w>
			<bbox_h>44</bbox_h>
		</bndbox>
		<rotated_bndbox>
			<rotated_bbox_cx>212</rotated_bbox_cx>
			<rotated_bbox_cy>175</rotated_bbox_cy>
			<rotated_bbox_w>44</rotated_bbox_w>
			<rotated_bbox_h>7</rotated_bbox_h>
			<rotated_bbox_theta>76.86598205566406</rotated_bbox_theta>
			<x1>204</x1>
			<y1>154</y1>
			<x2>211</x2>
			<y2>152</y2>
			<x3>221</x3>
			<y3>195</y3>
			<x4>214</x4>
			<y4>197</y4>
		</rotated_bndbox>
		<segm>
			<point-1>217,197</point-1>
			<point-2>219,194</point-2>
			<point-3>220,190</point-3>
			<point-4>218,187</point-4>
			<point-5>216,182</point-5>
			<point-6>216,176</point-6>
			<point-7>214,168</point-7>
			<point-8>213,160</point-8>
			<point-9>211,154</point-9>
			<point-10>209,153</point-10>
			<point-11>206,156</point-11>
			<point-12>208,163</point-12>
			<point-13>209,170</point-13>
			<point-14>210,177</point-14>
			<point-15>211,184</point-15>
			<point-16>213,191</point-16>
			<point-17>214,195</point-17>
		</segm>
	</object>
</annotation>