<annotation>
	<folder>JPEGImages</folder>
	<filename>000177.jpg</filename>
	<path>JPEGImages</path>
	<size>
		<width>438</width>
		<height>214</height>
		<depth>3</depth>
	</size>
	<object>
		<name>ship</name>
		<pose>Unspecified</pose>
		<truncated>0</truncated>
		<difficult>0</difficult>
		<bndbox>
			<xmin>54</xmin>
			<ymin>29</ymin>
			<xmax>64</xmax>
			<ymax>67</ymax>
			<bbox_w>10</bbox_w>
			<bbox_h>38</bbox_h>
		</bndbox>
		<rotated_bndbox>
			<rotated_bbox_cx>58</rotated_bbox_cx>
			<rotated_bbox_cy>48</rotated_bbox_cy>
			<rotated_bbox_w>38</rotated_bbox_w>
			<rotated_bbox_h>8</rotated_bbox_h>
			<rotated_bbox_theta>85.60128784179688</rotated_bbox_theta>
			<x1>53</x1>
			<y1>29</y1>
			<x2>61</x2>
			<y2>28</y2>
			<x3>64</x3>
			<y3>66</y3>
			<x4>56</x4>
			<y4>67</y4>
		</rotated_bndbox>
		<segm>
			<point-1>63,67</point-1>
			<point-2>64,60</point-2>
			<point-3>63,53</point-3>
			<point-4>63,47</point-4>
			<point-5>61,41</point-5>
			<point-6>59,36</point-6>
			<point-7>55,29</point-7>
			<point-8>54,34</point-8>
			<point-9>55,39</point-9>
			<point-10>55,43</point-10>
			<point-11>55,48</point-11>
			<point-12>55,53</point-12>
			<point-13>56,58</point-13>
			<point-14>57,64</point-14>
			<point-15>59,67</point-15>
		</segm>
	</object>
	<object>
		<name>ship</name>
		<pose>Unspecified</pose>
		<truncated>0</truncated>
		<difficult>0</difficult>
		<bndbox>
			<xmin>253</xmin>
			<ymin>17</ymin>
			<xmax>263</xmax>
			<ymax>42</ymax>
			<bbox_w>10</bbox_w>
			<bbox_h>25</bbox_h>
		</bndbox>
		<rotated_bndbox>
			<rotated_bbox_cx>257</rotated_bbox_cx>
			<rotated_bbox_cy>29</rotated_bbox_cy>
			<rotated_bbox_w>25</rotated_bbox_w>
			<rotated_bbox_h>9</rotated_bbox_h>
			<rotated_bbox_theta>84.2894058227539</rotated_bbox_theta>
			<x1>252</x1>
			<y1>17</y1>
			<x2>261</x2>
			<y2>16</y2>
			<x3>263</x3>
			<y3>41</y3>
			<x4>254</x4>
			<y4>42</y4>
		</rotated_bndbox>
		<segm>
			<point-1>263,41</point-1>
			<point-2>263,37</point-2>
			<point-3>263,32</point-3>
			<point-4>262,26</point-4>
			<point-5>259,22</point-5>
			<point-6>254,17</point-6>
			<point-7>253,22</point-7>
			<point-8>253,27</point-8>
			<point-9>254,32</point-9>
			<point-10>254,37</point-10>
			<point-11>257,40</point-11>
			<point-12>260,42</point-12>
		</segm>
	</object>
	<object>
		<name>ship</name>
		<pose>Unspecified</pose>
		<truncated>0</truncated>
		<difficult>0</difficult>
		<bndbox>
			<xmin>395</xmin>
			<ymin>167</ymin>
			<xmax>406</xmax>
			<ymax>196</ymax>
			<bbox_w>11</bbox_w>
			<bbox_h>29</bbox_h>
		</bndbox>
		<rotated_bndbox>
			<rotated_bbox_cx>400</rotated_bbox_cx>
			<rotated_bbox_cy>181</rotated_bbox_cy>
			<rotated_bbox_w>29</rotated_bbox_w>
			<rotated_bbox_h>9</rotated_bbox_h>
			<rotated_bbox_theta>82.40535736083984</rotated_bbox_theta>
			<x1>393</x1>
			<y1>167</y1>
			<x2>403</x2>
			<y2>165</y2>
			<x3>407</x3>
			<y3>195</y3>
			<x4>397</x4>
			<y4>196</y4>
		</rotated_bndbox>
		<segm>
			<point-1>403,196</point-1>
			<point-2>405,192</point-2>
			<point-3>406,186</point-3>
			<point-4>404,181</point-4>
			<point-5>403,177</point-5>
			<point-6>399,172</point-6>
			<point-7>395,167</point-7>
			<point-8>395,175</point-8>
			<point-9>396,182</point-9>
			<point-10>397,190</point-10>
			<point-11>398,194</point-11>
		</segm>
	</object>
</annotation>