<annotation>
	<folder>JPEGImages</folder>
	<filename>000193.jpg</filename>
	<path>JPEGImages</path>
	<size>
		<width>435</width>
		<height>357</height>
		<depth>3</depth>
	</size>
	<object>
		<name>ship</name>
		<pose>Unspecified</pose>
		<truncated>0</truncated>
		<difficult>0</difficult>
		<bndbox>
			<xmin>178</xmin>
			<ymin>253</ymin>
			<xmax>196</xmax>
			<ymax>304</ymax>
			<bbox_w>18</bbox_w>
			<bbox_h>51</bbox_h>
		</bndbox>
		<rotated_bndbox>
			<rotated_bbox_cx>185</rotated_bbox_cx>
			<rotated_bbox_cy>278</rotated_bbox_cy>
			<rotated_bbox_w>52</rotated_bbox_w>
			<rotated_bbox_h>11</rotated_bbox_h>
			<rotated_bbox_theta>71.56504821777344</rotated_bbox_theta>
			<x1>172</x1>
			<y1>255</y1>
			<x2>183</x2>
			<y2>252</y2>
			<x3>199</x3>
			<y3>302</y3>
			<x4>188</x4>
			<y4>305</y4>
		</rotated_bndbox>
		<segm>
			<point-1>194,304</point-1>
			<point-2>196,296</point-2>
			<point-3>194,285</point-3>
			<point-4>189,276</point-4>
			<point-5>186,268</point-5>
			<point-6>185,258</point-6>
			<point-7>180,253</point-7>
			<point-8>178,257</point-8>
			<point-9>179,268</point-9>
			<point-10>180,276</point-10>
			<point-11>182,285</point-11>
			<point-12>185,292</point-12>
			<point-13>188,299</point-13>
		</segm>
	</object>
	<object>
		<name>ship</name>
		<pose>Unspecified</pose>
		<truncated>0</truncated>
		<difficult>0</difficult>
		<bndbox>
			<xmin>287</xmin>
			<ymin>147</ymin>
			<xmax>300</xmax>
			<ymax>180</ymax>
			<bbox_w>13</bbox_w>
			<bbox_h>33</bbox_h>
		</bndbox>
		<rotated_bndbox>
			<rotated_bbox_cx>293</rotated_bbox_cx>
			<rotated_bbox_cy>163</rotated_bbox_cy>
			<rotated_bbox_w>32</rotated_bbox_w>
			<rotated_bbox_h>11</rotated_bbox_h>
			<rotated_bbox_theta>82.87498474121094</rotated_bbox_theta>
			<x1>285</x1>
			<y1>147</y1>
			<x2>297</x2>
			<y2>146</y2>
			<x3>301</x3>
			<y3>179</y3>
			<x4>289</x4>
			<y4>180</y4>
		</rotated_bndbox>
		<segm>
			<point-1>298,179</point-1>
			<point-2>297,171</point-2>
			<point-3>300,167</point-3>
			<point-4>296,162</point-4>
			<point-5>294,155</point-5>
			<point-6>292,147</point-6>
			<point-7>287,148</point-7>
			<point-8>288,156</point-8>
			<point-9>288,165</point-9>
			<point-10>289,173</point-10>
			<point-11>294,180</point-11>
		</segm>
	</object>
	<object>
		<name>ship</name>
		<pose>Unspecified</pose>
		<truncated>0</truncated>
		<difficult>0</difficult>
		<bndbox>
			<xmin>409</xmin>
			<ymin>303</ymin>
			<xmax>425</xmax>
			<ymax>346</ymax>
			<bbox_w>16</bbox_w>
			<bbox_h>43</bbox_h>
		</bndbox>
		<rotated_bndbox>
			<rotated_bbox_cx>415</rotated_bbox_cx>
			<rotated_bbox_cy>324</rotated_bbox_cy>
			<rotated_bbox_w>45</rotated_bbox_w>
			<rotated_bbox_h>11</rotated_bbox_h>
			<rotated_bbox_theta>70.20112609863281</rotated_bbox_theta>
			<x1>402</x1>
			<y1>305</y1>
			<x2>413</x2>
			<y2>301</y2>
			<x3>428</x3>
			<y3>343</y3>
			<x4>417</x4>
			<y4>347</y4>
		</rotated_bndbox>
		<segm>
			<point-1>423,346</point-1>
			<point-2>425,341</point-2>
			<point-3>425,333</point-3>
			<point-4>422,327</point-4>
			<point-5>420,322</point-5>
			<point-6>416,315</point-6>
			<point-7>416,308</point-7>
			<point-8>413,303</point-8>
			<point-9>409,303</point-9>
			<point-10>409,307</point-10>
			<point-11>409,314</point-11>
			<point-12>410,321</point-12>
			<point-13>412,329</point-13>
			<point-14>413,335</point-14>
			<point-15>416,340</point-15>
			<point-16>418,344</point-16>
		</segm>
	</object>
	<object>
		<name>ship</name>
		<pose>Unspecified</pose>
		<truncated>0</truncated>
		<difficult>0</difficult>
		<bndbox>
			<xmin>255</xmin>
			<ymin>279</ymin>
			<xmax>268</xmax>
			<ymax>323</ymax>
			<bbox_w>13</bbox_w>
			<bbox_h>44</bbox_h>
		</bndbox>
		<rotated_bndbox>
			<rotated_bbox_cx>261</rotated_bbox_cx>
			<rotated_bbox_cy>300</rotated_bbox_cy>
			<rotated_bbox_w>44</rotated_bbox_w>
			<rotated_bbox_h>6</rotated_bbox_h>
			<rotated_bbox_theta>76.75948333740234</rotated_bbox_theta>
			<x1>252</x1>
			<y1>279</y1>
			<x2>259</x2>
			<y2>278</y2>
			<x3>269</x3>
			<y3>321</y3>
			<x4>263</x4>
			<y4>323</y4>
		</rotated_bndbox>
		<segm>
			<point-1>265,323</point-1>
			<point-2>267,320</point-2>
			<point-3>268,316</point-3>
			<point-4>267,314</point-4>
			<point-5>265,311</point-5>
			<point-6>263,304</point-6>
			<point-7>263,299</point-7>
			<point-8>262,292</point-8>
			<point-9>261,289</point-9>
			<point-10>260,284</point-10>
			<point-11>259,281</point-11>
			<point-12>257,279</point-12>
			<point-13>255,280</point-13>
			<point-14>256,285</point-14>
			<point-15>257,290</point-15>
			<point-16>257,295</point-16>
			<point-17>258,300</point-17>
			<point-18>259,306</point-18>
			<point-19>261,313</point-19>
			<point-20>262,318</point-20>
			<point-21>263,323</point-21>
		</segm>
	</object>
</annotation>