<annotation>
	<folder>JPEGImages</folder>
	<filename>000180.jpg</filename>
	<path>JPEGImages</path>
	<size>
		<width>439</width>
		<height>296</height>
		<depth>3</depth>
	</size>
	<object>
		<name>ship</name>
		<pose>Unspecified</pose>
		<truncated>0</truncated>
		<difficult>0</difficult>
		<bndbox>
			<xmin>45</xmin>
			<ymin>150</ymin>
			<xmax>62</xmax>
			<ymax>198</ymax>
			<bbox_w>17</bbox_w>
			<bbox_h>48</bbox_h>
		</bndbox>
		<rotated_bndbox>
			<rotated_bbox_cx>52</rotated_bbox_cx>
			<rotated_bbox_cy>174</rotated_bbox_cy>
			<rotated_bbox_w>49</rotated_bbox_w>
			<rotated_bbox_h>12</rotated_bbox_h>
			<rotated_bbox_theta>74.05460357666016</rotated_bbox_theta>
			<x1>39</x1>
			<y1>151</y1>
			<x2>51</x2>
			<y2>148</y2>
			<x3>64</x3>
			<y3>196</y3>
			<x4>52</x4>
			<y4>200</y4>
		</rotated_bndbox>
		<segm>
			<point-1>60,198</point-1>
			<point-2>62,190</point-2>
			<point-3>61,183</point-3>
			<point-4>58,176</point-4>
			<point-5>54,168</point-5>
			<point-6>52,162</point-6>
			<point-7>50,156</point-7>
			<point-8>46,150</point-8>
			<point-9>45,160</point-9>
			<point-10>46,173</point-10>
			<point-11>48,183</point-11>
			<point-12>50,190</point-12>
			<point-13>54,196</point-13>
		</segm>
	</object>
	<object>
		<name>ship</name>
		<pose>Unspecified</pose>
		<truncated>0</truncated>
		<difficult>0</difficult>
		<bndbox>
			<xmin>153</xmin>
			<ymin>43</ymin>
			<xmax>163</xmax>
			<ymax>74</ymax>
			<bbox_w>10</bbox_w>
			<bbox_h>31</bbox_h>
		</bndbox>
		<rotated_bndbox>
			<rotated_bbox_cx>158</rotated_bbox_cx>
			<rotated_bbox_cy>58</rotated_bbox_cy>
			<rotated_bbox_w>31</rotated_bbox_w>
			<rotated_bbox_h>9</rotated_bbox_h>
			<rotated_bbox_theta>85.91438293457031</rotated_bbox_theta>
			<x1>152</x1>
			<y1>43</y1>
			<x2>161</x2>
			<y2>42</y2>
			<x3>163</x3>
			<y3>73</y3>
			<x4>154</x4>
			<y4>74</y4>
		</rotated_bndbox>
		<segm>
			<point-1>162,74</point-1>
			<point-2>162,69</point-2>
			<point-3>163,65</point-3>
			<point-4>163,60</point-4>
			<point-5>160,56</point-5>
			<point-6>159,50</point-6>
			<point-7>158,45</point-7>
			<point-8>155,43</point-8>
			<point-9>153,48</point-9>
			<point-10>154,57</point-10>
			<point-11>154,62</point-11>
			<point-12>155,67</point-12>
			<point-13>158,72</point-13>
		</segm>
	</object>
	<object>
		<name>ship</name>
		<pose>Unspecified</pose>
		<truncated>0</truncated>
		<difficult>0</difficult>
		<bndbox>
			<xmin>274</xmin>
			<ymin>198</ymin>
			<xmax>290</xmax>
			<ymax>242</ymax>
			<bbox_w>16</bbox_w>
			<bbox_h>44</bbox_h>
		</bndbox>
		<rotated_bndbox>
			<rotated_bbox_cx>281</rotated_bbox_cx>
			<rotated_bbox_cy>220</rotated_bbox_cy>
			<rotated_bbox_w>44</rotated_bbox_w>
			<rotated_bbox_h>10</rotated_bbox_h>
			<rotated_bbox_theta>67.83365631103516</rotated_bbox_theta>
			<x1>267</x1>
			<y1>201</y1>
			<x2>277</x2>
			<y2>197</y2>
			<x3>294</x3>
			<y3>239</y3>
			<x4>284</x4>
			<y4>243</y4>
		</rotated_bndbox>
		<segm>
			<point-1>288,242</point-1>
			<point-2>289,239</point-2>
			<point-3>290,233</point-3>
			<point-4>290,228</point-4>
			<point-5>287,223</point-5>
			<point-6>283,217</point-6>
			<point-7>281,210</point-7>
			<point-8>281,206</point-8>
			<point-9>279,201</point-9>
			<point-10>277,198</point-10>
			<point-11>274,200</point-11>
			<point-12>275,208</point-12>
			<point-13>275,215</point-13>
			<point-14>278,220</point-14>
			<point-15>278,225</point-15>
			<point-16>280,232</point-16>
			<point-17>282,236</point-17>
		</segm>
	</object>
	<object>
		<name>ship</name>
		<pose>Unspecified</pose>
		<truncated>0</truncated>
		<difficult>0</difficult>
		<bndbox>
			<xmin>394</xmin>
			<ymin>72</ymin>
			<xmax>406</xmax>
			<ymax>96</ymax>
			<bbox_w>12</bbox_w>
			<bbox_h>24</bbox_h>
		</bndbox>
		<rotated_bndbox>
			<rotated_bbox_cx>400</rotated_bbox_cx>
			<rotated_bbox_cy>83</rotated_bbox_cy>
			<rotated_bbox_w>24</rotated_bbox_w>
			<rotated_bbox_h>9</rotated_bbox_h>
			<rotated_bbox_theta>77.00537872314453</rotated_bbox_theta>
			<x1>393</x1>
			<y1>72</y1>
			<x2>402</x2>
			<y2>70</y2>
			<x3>408</x3>
			<y3>94</y3>
			<x4>398</x4>
			<y4>97</y4>
		</rotated_bndbox>
		<segm>
			<point-1>403,96</point-1>
			<point-2>406,93</point-2>
			<point-3>406,86</point-3>
			<point-4>404,79</point-4>
			<point-5>400,73</point-5>
			<point-6>396,72</point-6>
			<point-7>394,77</point-7>
			<point-8>396,85</point-8>
			<point-9>397,90</point-9>
			<point-10>399,94</point-10>
		</segm>
	</object>
	<object>
		<name>ship</name>
		<pose>Unspecified</pose>
		<truncated>0</truncated>
		<difficult>0</difficult>
		<bndbox>
			<xmin>119</xmin>
			<ymin>172</ymin>
			<xmax>134</xmax>
			<ymax>221</ymax>
			<bbox_w>15</bbox_w>
			<bbox_h>49</bbox_h>
		</bndbox>
		<rotated_bndbox>
			<rotated_bbox_cx>127</rotated_bbox_cx>
			<rotated_bbox_cy>196</rotated_bbox_cy>
			<rotated_bbox_w>50</rotated_bbox_w>
			<rotated_bbox_h>7</rotated_bbox_h>
			<rotated_bbox_theta>78.69007110595703</rotated_bbox_theta>
			<x1>118</x1>
			<y1>172</y1>
			<x2>126</x2>
			<y2>171</y2>
			<x3>136</x3>
			<y3>220</y3>
			<x4>128</x4>
			<y4>221</y4>
		</rotated_bndbox>
		<segm>
			<point-1>132,221</point-1>
			<point-2>134,215</point-2>
			<point-3>134,210</point-3>
			<point-4>130,201</point-4>
			<point-5>129,191</point-5>
			<point-6>127,181</point-6>
			<point-7>125,174</point-7>
			<point-8>122,172</point-8>
			<point-9>119,173</point-9>
			<point-10>122,180</point-10>
			<point-11>122,186</point-11>
			<point-12>123,195</point-12>
			<point-13>125,202</point-13>
			<point-14>126,210</point-14>
			<point-15>127,215</point-15>
			<point-16>128,219</point-16>
		</segm>
	</object>
</annotation>