<annotation>
	<folder>JPEGImages</folder>
	<filename>000214.jpg</filename>
	<path>JPEGImages</path>
	<size>
		<width>496</width>
		<height>303</height>
		<depth>3</depth>
	</size>
	<object>
		<name>ship</name>
		<pose>Unspecified</pose>
		<truncated>0</truncated>
		<difficult>0</difficult>
		<bndbox>
			<xmin>345</xmin>
			<ymin>36</ymin>
			<xmax>373</xmax>
			<ymax>65</ymax>
			<bbox_w>28</bbox_w>
			<bbox_h>29</bbox_h>
		</bndbox>
		<rotated_bndbox>
			<rotated_bbox_cx>359</rotated_bbox_cx>
			<rotated_bbox_cy>49</rotated_bbox_cy>
			<rotated_bbox_w>14</rotated_bbox_w>
			<rotated_bbox_h>38</rotated_bbox_h>
			<rotated_bbox_theta>45.0</rotated_bbox_theta>
			<x1>341</x1>
			<y1>57</y1>
			<x2>368</x2>
			<y2>30</y2>
			<x3>378</x3>
			<y3>41</y3>
			<x4>351</x4>
			<y4>68</y4>
		</rotated_bndbox>
		<segm>
			<point-1>351,65</point-1>
			<point-2>361,58</point-2>
			<point-3>368,52</point-3>
			<point-4>373,43</point-4>
			<point-5>373,36</point-5>
			<point-6>365,36</point-6>
			<point-7>358,41</point-7>
			<point-8>351,49</point-8>
			<point-9>345,54</point-9>
			<point-10>345,62</point-10>
		</segm>
	</object>
	<object>
		<name>ship</name>
		<pose>Unspecified</pose>
		<truncated>0</truncated>
		<difficult>0</difficult>
		<bndbox>
			<xmin>225</xmin>
			<ymin>223</ymin>
			<xmax>239</xmax>
			<ymax>251</ymax>
			<bbox_w>14</bbox_w>
			<bbox_h>28</bbox_h>
		</bndbox>
		<rotated_bndbox>
			<rotated_bbox_cx>231</rotated_bbox_cx>
			<rotated_bbox_cy>236</rotated_bbox_cy>
			<rotated_bbox_w>28</rotated_bbox_w>
			<rotated_bbox_h>12</rotated_bbox_h>
			<rotated_bbox_theta>77.47119140625</rotated_bbox_theta>
			<x1>222</x1>
			<y1>223</y1>
			<x2>235</x2>
			<y2>221</y2>
			<x3>241</x3>
			<y3>249</y3>
			<x4>228</x4>
			<y4>252</y4>
		</rotated_bndbox>
		<segm>
			<point-1>234,251</point-1>
			<point-2>238,247</point-2>
			<point-3>239,239</point-3>
			<point-4>237,230</point-4>
			<point-5>232,224</point-5>
			<point-6>227,223</point-6>
			<point-7>225,230</point-7>
			<point-8>226,239</point-8>
			<point-9>230,248</point-9>
		</segm>
	</object>
	<object>
		<name>ship</name>
		<pose>Unspecified</pose>
		<truncated>0</truncated>
		<difficult>0</difficult>
		<bndbox>
			<xmin>198</xmin>
			<ymin>136</ymin>
			<xmax>211</xmax>
			<ymax>162</ymax>
			<bbox_w>13</bbox_w>
			<bbox_h>26</bbox_h>
		</bndbox>
		<rotated_bndbox>
			<rotated_bbox_cx>204</rotated_bbox_cx>
			<rotated_bbox_cy>149</rotated_bbox_cy>
			<rotated_bbox_w>26</rotated_bbox_w>
			<rotated_bbox_h>12</rotated_bbox_h>
			<rotated_bbox_theta>83.6598129272461</rotated_bbox_theta>
			<x1>197</x1>
			<y1>136</y1>
			<x2>209</x2>
			<y2>135</y2>
			<x3>212</x3>
			<y3>161</y3>
			<x4>200</x4>
			<y4>162</y4>
		</rotated_bndbox>
		<segm>
			<point-1>206,162</point-1>
			<point-2>210,157</point-2>
			<point-3>211,148</point-3>
			<point-4>210,139</point-4>
			<point-5>204,136</point-5>
			<point-6>199,137</point-6>
			<point-7>198,144</point-7>
			<point-8>200,152</point-8>
			<point-9>201,158</point-9>
		</segm>
	</object>
	<object>
		<name>ship</name>
		<pose>Unspecified</pose>
		<truncated>0</truncated>
		<difficult>0</difficult>
		<bndbox>
			<xmin>63</xmin>
			<ymin>124</ymin>
			<xmax>77</xmax>
			<ymax>151</ymax>
			<bbox_w>14</bbox_w>
			<bbox_h>27</bbox_h>
		</bndbox>
		<rotated_bndbox>
			<rotated_bbox_cx>68</rotated_bbox_cx>
			<rotated_bbox_cy>137</rotated_bbox_cy>
			<rotated_bbox_w>13</rotated_bbox_w>
			<rotated_bbox_h>27</rotated_bbox_h>
			<rotated_bbox_theta>10.61965560913086</rotated_bbox_theta>
			<x1>59</x1>
			<y1>149</y1>
			<x2>64</x2>
			<y2>122</y2>
			<x3>78</x3>
			<y3>125</y3>
			<x4>73</x4>
			<y4>151</y4>
		</rotated_bndbox>
		<segm>
			<point-1>69,151</point-1>
			<point-2>74,147</point-2>
			<point-3>75,140</point-3>
			<point-4>77,131</point-4>
			<point-5>72,124</point-5>
			<point-6>67,124</point-6>
			<point-7>63,130</point-7>
			<point-8>63,138</point-8>
			<point-9>64,145</point-9>
		</segm>
	</object>
	<object>
		<name>ship</name>
		<pose>Unspecified</pose>
		<truncated>0</truncated>
		<difficult>0</difficult>
		<bndbox>
			<xmin>22</xmin>
			<ymin>278</ymin>
			<xmax>30</xmax>
			<ymax>296</ymax>
			<bbox_w>8</bbox_w>
			<bbox_h>18</bbox_h>
		</bndbox>
		<rotated_bndbox>
			<rotated_bbox_cx>26</rotated_bbox_cx>
			<rotated_bbox_cy>287</rotated_bbox_cy>
			<rotated_bbox_w>8</rotated_bbox_w>
			<rotated_bbox_h>18</rotated_bbox_h>
			<rotated_bbox_theta>0.0</rotated_bbox_theta>
			<x1>22</x1>
			<y1>296</y1>
			<x2>22</x2>
			<y2>278</y2>
			<x3>30</x3>
			<y3>278</y3>
			<x4>30</x4>
			<y4>296</y4>
		</rotated_bndbox>
		<segm>
			<point-1>28,296</point-1>
			<point-2>30,293</point-2>
			<point-3>30,286</point-3>
			<point-4>28,282</point-4>
			<point-5>25,278</point-5>
			<point-6>22,278</point-6>
			<point-7>22,286</point-7>
			<point-8>23,291</point-8>
		</segm>
	</object>
	<object>
		<name>ship</name>
		<pose>Unspecified</pose>
		<truncated>0</truncated>
		<difficult>0</difficult>
		<bndbox>
			<xmin>37</xmin>
			<ymin>184</ymin>
			<xmax>45</xmax>
			<ymax>199</ymax>
			<bbox_w>8</bbox_w>
			<bbox_h>15</bbox_h>
		</bndbox>
		<rotated_bndbox>
			<rotated_bbox_cx>40</rotated_bbox_cx>
			<rotated_bbox_cy>191</rotated_bbox_cy>
			<rotated_bbox_w>15</rotated_bbox_w>
			<rotated_bbox_h>7</rotated_bbox_h>
			<rotated_bbox_theta>68.19859313964844</rotated_bbox_theta>
			<x1>34</x1>
			<y1>186</y1>
			<x2>40</x2>
			<y2>183</y2>
			<x3>46</x3>
			<y3>197</y3>
			<x4>39</x4>
			<y4>200</y4>
		</rotated_bndbox>
		<segm>
			<point-1>43,199</point-1>
			<point-2>45,194</point-2>
			<point-3>43,189</point-3>
			<point-4>40,184</point-4>
			<point-5>37,185</point-5>
			<point-6>37,191</point-6>
			<point-7>38,196</point-7>
		</segm>
	</object>
</annotation>