<annotation>
	<folder>JPEGImages</folder>
	<filename>000206.jpg</filename>
	<path>JPEGImages</path>
	<size>
		<width>440</width>
		<height>326</height>
		<depth>3</depth>
	</size>
	<object>
		<name>ship</name>
		<pose>Unspecified</pose>
		<truncated>0</truncated>
		<difficult>0</difficult>
		<bndbox>
			<xmin>206</xmin>
			<ymin>264</ymin>
			<xmax>234</xmax>
			<ymax>293</ymax>
			<bbox_w>28</bbox_w>
			<bbox_h>29</bbox_h>
		</bndbox>
		<rotated_bndbox>
			<rotated_bbox_cx>220</rotated_bbox_cx>
			<rotated_bbox_cy>278</rotated_bbox_cy>
			<rotated_bbox_w>15</rotated_bbox_w>
			<rotated_bbox_h>34</rotated_bbox_h>
			<rotated_bbox_theta>51.34019470214844</rotated_bbox_theta>
			<x1>202</x1>
			<y1>282</y1>
			<x2>228</x2>
			<y2>261</y2>
			<x3>238</x3>
			<y3>273</y3>
			<x4>212</x4>
			<y4>295</y4>
		</rotated_bndbox>
		<segm>
			<point-1>213,293</point-1>
			<point-2>219,289</point-2>
			<point-3>227,283</point-3>
			<point-4>232,276</point-4>
			<point-5>234,268</point-5>
			<point-6>228,264</point-6>
			<point-7>219,269</point-7>
			<point-8>214,273</point-8>
			<point-9>209,278</point-9>
			<point-10>206,284</point-10>
			<point-11>208,290</point-11>
		</segm>
	</object>
	<object>
		<name>ship</name>
		<pose>Unspecified</pose>
		<truncated>0</truncated>
		<difficult>0</difficult>
		<bndbox>
			<xmin>291</xmin>
			<ymin>171</ymin>
			<xmax>299</xmax>
			<ymax>179</ymax>
			<bbox_w>8</bbox_w>
			<bbox_h>8</bbox_h>
		</bndbox>
		<rotated_bndbox>
			<rotated_bbox_cx>295</rotated_bbox_cx>
			<rotated_bbox_cy>175</rotated_bbox_cy>
			<rotated_bbox_w>7</rotated_bbox_w>
			<rotated_bbox_h>8</rotated_bbox_h>
			<rotated_bbox_theta>75.96376037597656</rotated_bbox_theta>
			<x1>290</x1>
			<y1>172</y1>
			<x2>298</x2>
			<y2>170</y2>
			<x3>300</x3>
			<y3>178</y3>
			<x4>292</x4>
			<y4>179</y4>
		</rotated_bndbox>
		<segm>
			<point-1>296,179</point-1>
			<point-2>299,178</point-2>
			<point-3>299,174</point-3>
			<point-4>297,171</point-4>
			<point-5>293,172</point-5>
			<point-6>291,175</point-6>
			<point-7>292,179</point-7>
		</segm>
	</object>
	<object>
		<name>ship</name>
		<pose>Unspecified</pose>
		<truncated>0</truncated>
		<difficult>0</difficult>
		<bndbox>
			<xmin>319</xmin>
			<ymin>98</ymin>
			<xmax>331</xmax>
			<ymax>111</ymax>
			<bbox_w>12</bbox_w>
			<bbox_h>13</bbox_h>
		</bndbox>
		<rotated_bndbox>
			<rotated_bbox_cx>324</rotated_bbox_cx>
			<rotated_bbox_cy>104</rotated_bbox_cy>
			<rotated_bbox_w>6</rotated_bbox_w>
			<rotated_bbox_h>15</rotated_bbox_h>
			<rotated_bbox_theta>33.690067291259766</rotated_bbox_theta>
			<x1>317</x1>
			<y1>109</y1>
			<x2>326</x2>
			<y2>96</y2>
			<x3>331</x3>
			<y3>99</y3>
			<x4>323</x4>
			<y4>113</y4>
		</rotated_bndbox>
		<segm>
			<point-1>323,111</point-1>
			<point-2>326,109</point-2>
			<point-3>328,106</point-3>
			<point-4>330,103</point-4>
			<point-5>331,100</point-5>
			<point-6>329,98</point-6>
			<point-7>325,98</point-7>
			<point-8>324,101</point-8>
			<point-9>321,104</point-9>
			<point-10>319,107</point-10>
			<point-11>320,111</point-11>
		</segm>
	</object>
</annotation>