<annotation>
	<folder>JPEGImages</folder>
	<filename>000306.jpg</filename>
	<path>JPEGImages</path>
	<size>
		<width>500</width>
		<height>327</height>
		<depth>3</depth>
	</size>
	<object>
		<name>ship</name>
		<pose>Unspecified</pose>
		<truncated>0</truncated>
		<difficult>0</difficult>
		<bndbox>
			<xmin>105</xmin>
			<ymin>64</ymin>
			<xmax>139</xmax>
			<ymax>171</ymax>
			<bbox_w>34</bbox_w>
			<bbox_h>107</bbox_h>
		</bndbox>
		<rotated_bndbox>
			<rotated_bbox_cx>122</rotated_bbox_cx>
			<rotated_bbox_cy>117</rotated_bbox_cy>
			<rotated_bbox_w>108</rotated_bbox_w>
			<rotated_bbox_h>21</rotated_bbox_h>
			<rotated_bbox_theta>75.96376037597656</rotated_bbox_theta>
			<x1>98</x1>
			<y1>67</y1>
			<x2>119</x2>
			<y2>62</y2>
			<x3>145</x3>
			<y3>167</y3>
			<x4>124</x4>
			<y4>172</y4>
		</rotated_bndbox>
		<segm>
			<point-1>132,171</point-1>
			<point-2>136,161</point-2>
			<point-3>136,151</point-3>
			<point-4>139,141</point-4>
			<point-5>137,133</point-5>
			<point-6>131,123</point-6>
			<point-7>127,113</point-7>
			<point-8>126,102</point-8>
			<point-9>124,92</point-9>
			<point-10>119,81</point-10>
			<point-11>116,68</point-11>
			<point-12>112,64</point-12>
			<point-13>105,70</point-13>
			<point-14>108,82</point-14>
			<point-15>108,92</point-15>
			<point-16>108,103</point-16>
			<point-17>111,111</point-17>
			<point-18>113,120</point-18>
			<point-19>114,130</point-19>
			<point-20>117,142</point-20>
			<point-21>120,147</point-21>
			<point-22>123,155</point-22>
			<point-23>125,165</point-23>
		</segm>
	</object>
</annotation>