<annotation>
	<folder>JPEGImages</folder>
	<filename>000453.jpg</filename>
	<path>JPEGImages</path>
	<size>
		<width>500</width>
		<height>335</height>
		<depth>3</depth>
	</size>
	<object>
		<name>ship</name>
		<pose>Unspecified</pose>
		<truncated>0</truncated>
		<difficult>0</difficult>
		<bndbox>
			<xmin>207</xmin>
			<ymin>108</ymin>
			<xmax>248</xmax>
			<ymax>194</ymax>
			<bbox_w>41</bbox_w>
			<bbox_h>86</bbox_h>
		</bndbox>
		<rotated_bndbox>
			<rotated_bbox_cx>232</rotated_bbox_cx>
			<rotated_bbox_cy>150</rotated_bbox_cy>
			<rotated_bbox_w>90</rotated_bbox_w>
			<rotated_bbox_h>31</rotated_bbox_h>
			<rotated_bbox_theta>76.4295654296875</rotated_bbox_theta>
			<x1>206</x1>
			<y1>110</y1>
			<x2>237</x2>
			<y2>102</y2>
			<x3>258</x3>
			<y3>190</y3>
			<x4>227</x4>
			<y4>197</y4>
		</rotated_bndbox>
		<segm>
			<point-1>243,194</point-1>
			<point-2>248,191</point-2>
			<point-3>248,184</point-3>
			<point-4>245,175</point-4>
			<point-5>244,168</point-5>
			<point-6>244,160</point-6>
			<point-7>248,157</point-7>
			<point-8>248,148</point-8>
			<point-9>245,139</point-9>
			<point-10>243,128</point-10>
			<point-11>242,124</point-11>
			<point-12>238,117</point-12>
			<point-13>232,112</point-13>
			<point-14>225,108</point-14>
			<point-15>221,108</point-15>
			<point-16>211,109</point-16>
			<point-17>207,113</point-17>
			<point-18>210,123</point-18>
			<point-19>214,127</point-19>
			<point-20>217,134</point-20>
			<point-21>219,140</point-21>
			<point-22>219,145</point-22>
			<point-23>219,152</point-23>
			<point-24>220,162</point-24>
			<point-25>221,171</point-25>
			<point-26>224,179</point-26>
			<point-27>227,182</point-27>
			<point-28>233,185</point-28>
			<point-29>236,190</point-29>
			<point-30>238,194</point-30>
		</segm>
	</object>
</annotation>