<annotation>
	<folder>JPEGImages</folder>
	<filename>000414.jpg</filename>
	<path>JPEGImages</path>
	<size>
		<width>500</width>
		<height>340</height>
		<depth>3</depth>
	</size>
	<object>
		<name>ship</name>
		<pose>Unspecified</pose>
		<truncated>0</truncated>
		<difficult>0</difficult>
		<bndbox>
			<xmin>37</xmin>
			<ymin>44</ymin>
			<xmax>88</xmax>
			<ymax>177</ymax>
			<bbox_w>51</bbox_w>
			<bbox_h>133</bbox_h>
		</bndbox>
		<rotated_bndbox>
			<rotated_bbox_cx>61</rotated_bbox_cx>
			<rotated_bbox_cy>109</rotated_bbox_cy>
			<rotated_bbox_w>134</rotated_bbox_w>
			<rotated_bbox_h>48</rotated_bbox_h>
			<rotated_bbox_theta>83.6598129272461</rotated_bbox_theta>
			<x1>30</x1>
			<y1>45</y1>
			<x2>78</x2>
			<y2>39</y2>
			<x3>93</x3>
			<y3>173</y3>
			<x4>45</x4>
			<y4>178</y4>
		</rotated_bndbox>
		<segm>
			<point-1>67,175</point-1>
			<point-2>76,169</point-2>
			<point-3>80,164</point-3>
			<point-4>78,153</point-4>
			<point-5>78,145</point-5>
			<point-6>84,140</point-6>
			<point-7>88,134</point-7>
			<point-8>88,126</point-8>
			<point-9>86,110</point-9>
			<point-10>82,100</point-10>
			<point-11>78,92</point-11>
			<point-12>70,88</point-12>
			<point-13>63,84</point-13>
			<point-14>59,75</point-14>
			<point-15>57,66</point-15>
			<point-16>55,52</point-16>
			<point-17>48,45</point-17>
			<point-18>41,44</point-18>
			<point-19>39,51</point-19>
			<point-20>39,62</point-20>
			<point-21>41,72</point-21>
			<point-22>43,83</point-22>
			<point-23>43,90</point-23>
			<point-24>39,97</point-24>
			<point-25>37,103</point-25>
			<point-26>38,114</point-26>
			<point-27>39,121</point-27>
			<point-28>41,132</point-28>
			<point-29>42,140</point-29>
			<point-30>42,150</point-30>
			<point-31>46,154</point-31>
			<point-32>51,157</point-32>
			<point-33>54,168</point-33>
			<point-34>56,177</point-34>
			<point-35>62,177</point-35>
		</segm>
	</object>
</annotation>