<annotation>
	<folder>JPEGImages</folder>
	<filename>000571.jpg</filename>
	<path>JPEGImages</path>
	<size>
		<width>500</width>
		<height>373</height>
		<depth>3</depth>
	</size>
	<object>
		<name>ship</name>
		<pose>Unspecified</pose>
		<truncated>0</truncated>
		<difficult>0</difficult>
		<bndbox>
			<xmin>236</xmin>
			<ymin>125</ymin>
			<xmax>286</xmax>
			<ymax>264</ymax>
			<bbox_w>50</bbox_w>
			<bbox_h>139</bbox_h>
		</bndbox>
		<rotated_bndbox>
			<rotated_bbox_cx>261</rotated_bbox_cx>
			<rotated_bbox_cy>194</rotated_bbox_cy>
			<rotated_bbox_w>139</rotated_bbox_w>
			<rotated_bbox_h>49</rotated_bbox_h>
			<rotated_bbox_theta>89.4791488647461</rotated_bbox_theta>
			<x1>235</x1>
			<y1>125</y1>
			<x2>285</x2>
			<y2>124</y2>
			<x3>286</x3>
			<y3>263</y3>
			<x4>237</x4>
			<y4>264</y4>
		</rotated_bndbox>
		<segm>
			<point-1>265,264</point-1>
			<point-2>274,259</point-2>
			<point-3>272,246</point-3>
			<point-4>277,238</point-4>
			<point-5>284,228</point-5>
			<point-6>284,216</point-6>
			<point-7>286,207</point-7>
			<point-8>285,191</point-8>
			<point-9>278,176</point-9>
			<point-10>270,170</point-10>
			<point-11>262,170</point-11>
			<point-12>257,154</point-12>
			<point-13>254,138</point-13>
			<point-14>250,127</point-14>
			<point-15>242,125</point-15>
			<point-16>236,132</point-16>
			<point-17>240,144</point-17>
			<point-18>239,153</point-18>
			<point-19>241,168</point-19>
			<point-20>241,179</point-20>
			<point-21>243,195</point-21>
			<point-22>246,208</point-22>
			<point-23>248,220</point-23>
			<point-24>250,230</point-24>
			<point-25>246,233</point-25>
			<point-26>237,231</point-26>
			<point-27>237,242</point-27>
			<point-28>241,250</point-28>
			<point-29>250,253</point-29>
			<point-30>257,254</point-30>
			<point-31>262,257</point-31>
		</segm>
	</object>
</annotation>