<annotation>
	<folder>JPEGImages</folder>
	<filename>000638.jpg</filename>
	<path>JPEGImages</path>
	<size>
		<width>501</width>
		<height>320</height>
		<depth>3</depth>
	</size>
	<object>
		<name>ship</name>
		<pose>Unspecified</pose>
		<truncated>0</truncated>
		<difficult>0</difficult>
		<bndbox>
			<xmin>180</xmin>
			<ymin>96</ymin>
			<xmax>208</xmax>
			<ymax>123</ymax>
			<bbox_w>28</bbox_w>
			<bbox_h>27</bbox_h>
		</bndbox>
		<rotated_bndbox>
			<rotated_bbox_cx>195</rotated_bbox_cx>
			<rotated_bbox_cy>109</rotated_bbox_cy>
			<rotated_bbox_w>13</rotated_bbox_w>
			<rotated_bbox_h>34</rotated_bbox_h>
			<rotated_bbox_theta>49.89909744262695</rotated_bbox_theta>
			<x1>177</x1>
			<y1>115</y1>
			<x2>204</x2>
			<y2>93</y2>
			<x3>212</x3>
			<y3>103</y3>
			<x4>186</x4>
			<y4>125</y4>
		</rotated_bndbox>
		<segm>
			<point-1>186,123</point-1>
			<point-2>193,119</point-2>
			<point-3>199,115</point-3>
			<point-4>203,110</point-4>
			<point-5>207,105</point-5>
			<point-6>208,99</point-6>
			<point-7>206,96</point-7>
			<point-8>200,97</point-8>
			<point-9>196,101</point-9>
			<point-10>192,105</point-10>
			<point-11>186,109</point-11>
			<point-12>181,113</point-12>
			<point-13>180,117</point-13>
			<point-14>183,122</point-14>
		</segm>
	</object>
</annotation>