<annotation>
	<folder>JPEGImages</folder>
	<filename>000873.jpg</filename>
	<path>JPEGImages</path>
	<size>
		<width>502</width>
		<height>329</height>
		<depth>3</depth>
	</size>
	<object>
		<name>ship</name>
		<pose>Unspecified</pose>
		<truncated>0</truncated>
		<difficult>0</difficult>
		<bndbox>
			<xmin>309</xmin>
			<ymin>87</ymin>
			<xmax>323</xmax>
			<ymax>134</ymax>
			<bbox_w>14</bbox_w>
			<bbox_h>47</bbox_h>
		</bndbox>
		<rotated_bndbox>
			<rotated_bbox_cx>316</rotated_bbox_cx>
			<rotated_bbox_cy>110</rotated_bbox_cy>
			<rotated_bbox_w>47</rotated_bbox_w>
			<rotated_bbox_h>14</rotated_bbox_h>
			<rotated_bbox_theta>90.0</rotated_bbox_theta>
			<x1>309</x1>
			<y1>87</y1>
			<x2>323</x2>
			<y2>87</y2>
			<x3>323</x3>
			<y3>134</y3>
			<x4>309</x4>
			<y4>134</y4>
		</rotated_bndbox>
		<segm>
			<point-1>317,134</point-1>
			<point-2>321,125</point-2>
			<point-3>323,116</point-3>
			<point-4>321,102</point-4>
			<point-5>320,91</point-5>
			<point-6>317,87</point-6>
			<point-7>312,87</point-7>
			<point-8>311,95</point-8>
			<point-9>310,106</point-9>
			<point-10>309,115</point-10>
			<point-11>309,125</point-11>
			<point-12>310,134</point-12>
		</segm>
	</object>
	<object>
		<name>ship</name>
		<pose>Unspecified</pose>
		<truncated>0</truncated>
		<difficult>0</difficult>
		<bndbox>
			<xmin>477</xmin>
			<ymin>61</ymin>
			<xmax>489</xmax>
			<ymax>108</ymax>
			<bbox_w>12</bbox_w>
			<bbox_h>47</bbox_h>
		</bndbox>
		<rotated_bndbox>
			<rotated_bbox_cx>483</rotated_bbox_cx>
			<rotated_bbox_cy>84</rotated_bbox_cy>
			<rotated_bbox_w>47</rotated_bbox_w>
			<rotated_bbox_h>12</rotated_bbox_h>
			<rotated_bbox_theta>90.0</rotated_bbox_theta>
			<x1>477</x1>
			<y1>61</y1>
			<x2>489</x2>
			<y2>61</y2>
			<x3>489</x3>
			<y3>108</y3>
			<x4>477</x4>
			<y4>108</y4>
		</rotated_bndbox>
		<segm>
			<point-1>484,108</point-1>
			<point-2>487,94</point-2>
			<point-3>489,80</point-3>
			<point-4>488,66</point-4>
			<point-5>485,61</point-5>
			<point-6>477,62</point-6>
			<point-7>478,73</point-7>
			<point-8>477,85</point-8>
			<point-9>478,96</point-9>
			<point-10>478,108</point-10>
		</segm>
	</object>
</annotation>