<annotation>
	<folder>JPEGImages</folder>
	<filename>001106.jpg</filename>
	<path>JPEGImages</path>
	<size>
		<width>497</width>
		<height>308</height>
		<depth>3</depth>
	</size>
	<object>
		<name>ship</name>
		<pose>Unspecified</pose>
		<truncated>0</truncated>
		<difficult>0</difficult>
		<bndbox>
			<xmin>208</xmin>
			<ymin>31</ymin>
			<xmax>218</xmax>
			<ymax>48</ymax>
			<bbox_w>10</bbox_w>
			<bbox_h>17</bbox_h>
		</bndbox>
		<rotated_bndbox>
			<rotated_bbox_cx>213</rotated_bbox_cx>
			<rotated_bbox_cy>39</rotated_bbox_cy>
			<rotated_bbox_w>10</rotated_bbox_w>
			<rotated_bbox_h>17</rotated_bbox_h>
			<rotated_bbox_theta>0.0</rotated_bbox_theta>
			<x1>208</x1>
			<y1>48</y1>
			<x2>208</x2>
			<y2>31</y2>
			<x3>218</x3>
			<y3>31</y3>
			<x4>218</x4>
			<y4>48</y4>
		</rotated_bndbox>
		<segm>
			<point-1>218,47</point-1>
			<point-2>218,39</point-2>
			<point-3>217,33</point-3>
			<point-4>211,31</point-4>
			<point-5>208,36</point-5>
			<point-6>208,42</point-6>
			<point-7>210,48</point-7>
		</segm>
	</object>
	<object>
		<name>ship</name>
		<pose>Unspecified</pose>
		<truncated>0</truncated>
		<difficult>0</difficult>
		<bndbox>
			<xmin>215</xmin>
			<ymin>132</ymin>
			<xmax>235</xmax>
			<ymax>152</ymax>
			<bbox_w>20</bbox_w>
			<bbox_h>20</bbox_h>
		</bndbox>
		<rotated_bndbox>
			<rotated_bbox_cx>224</rotated_bbox_cx>
			<rotated_bbox_cy>143</rotated_bbox_cy>
			<rotated_bbox_w>25</rotated_bbox_w>
			<rotated_bbox_h>11</rotated_bbox_h>
			<rotated_bbox_theta>52.43141174316406</rotated_bbox_theta>
			<x1>212</x1>
			<y1>136</y1>
			<x2>221</x2>
			<y2>129</y2>
			<x3>237</x3>
			<y3>150</y3>
			<x4>228</x4>
			<y4>157</y4>
		</rotated_bndbox>
		<segm>
			<point-1>235,152</point-1>
			<point-2>234,146</point-2>
			<point-3>228,139</point-3>
			<point-4>224,133</point-4>
			<point-5>219,132</point-5>
			<point-6>215,135</point-6>
			<point-7>215,140</point-7>
			<point-8>218,143</point-8>
			<point-9>222,148</point-9>
			<point-10>226,151</point-10>
		</segm>
	</object>
	<object>
		<name>ship</name>
		<pose>Unspecified</pose>
		<truncated>0</truncated>
		<difficult>0</difficult>
		<bndbox>
			<xmin>250</xmin>
			<ymin>265</ymin>
			<xmax>274</xmax>
			<ymax>285</ymax>
			<bbox_w>24</bbox_w>
			<bbox_h>20</bbox_h>
		</bndbox>
		<rotated_bndbox>
			<rotated_bbox_cx>261</rotated_bbox_cx>
			<rotated_bbox_cy>275</rotated_bbox_cy>
			<rotated_bbox_w>27</rotated_bbox_w>
			<rotated_bbox_h>13</rotated_bbox_h>
			<rotated_bbox_theta>33.690067291259766</rotated_bbox_theta>
			<x1>246</x1>
			<y1>272</y1>
			<x2>253</x2>
			<y2>262</y2>
			<x3>276</x3>
			<y3>277</y3>
			<x4>269</x4>
			<y4>288</y4>
		</rotated_bndbox>
		<segm>
			<point-1>274,281</point-1>
			<point-2>273,275</point-2>
			<point-3>266,271</point-3>
			<point-4>261,267</point-4>
			<point-5>256,265</point-5>
			<point-6>251,266</point-6>
			<point-7>250,270</point-7>
			<point-8>253,276</point-8>
			<point-9>260,282</point-9>
			<point-10>268,285</point-10>
		</segm>
	</object>
	<object>
		<name>ship</name>
		<pose>Unspecified</pose>
		<truncated>0</truncated>
		<difficult>0</difficult>
		<bndbox>
			<xmin>343</xmin>
			<ymin>156</ymin>
			<xmax>357</xmax>
			<ymax>185</ymax>
			<bbox_w>14</bbox_w>
			<bbox_h>29</bbox_h>
		</bndbox>
		<rotated_bndbox>
			<rotated_bbox_cx>348</rotated_bbox_cx>
			<rotated_bbox_cy>170</rotated_bbox_cy>
			<rotated_bbox_w>30</rotated_bbox_w>
			<rotated_bbox_h>12</rotated_bbox_h>
			<rotated_bbox_theta>82.87498474121094</rotated_bbox_theta>
			<x1>340</x1>
			<y1>156</y1>
			<x2>353</x2>
			<y2>155</y2>
			<x3>357</x3>
			<y3>185</y3>
			<x4>344</x4>
			<y4>186</y4>
		</rotated_bndbox>
		<segm>
			<point-1>357,185</point-1>
			<point-2>355,177</point-2>
			<point-3>355,169</point-3>
			<point-4>354,162</point-4>
			<point-5>350,156</point-5>
			<point-6>346,156</point-6>
			<point-7>343,162</point-7>
			<point-8>343,174</point-8>
			<point-9>346,179</point-9>
			<point-10>350,182</point-10>
		</segm>
	</object>
	<object>
		<name>ship</name>
		<pose>Unspecified</pose>
		<truncated>0</truncated>
		<difficult>0</difficult>
		<bndbox>
			<xmin>423</xmin>
			<ymin>191</ymin>
			<xmax>434</xmax>
			<ymax>221</ymax>
			<bbox_w>11</bbox_w>
			<bbox_h>30</bbox_h>
		</bndbox>
		<rotated_bndbox>
			<rotated_bbox_cx>428</rotated_bbox_cx>
			<rotated_bbox_cy>206</rotated_bbox_cy>
			<rotated_bbox_w>11</rotated_bbox_w>
			<rotated_bbox_h>30</rotated_bbox_h>
			<rotated_bbox_theta>0.0</rotated_bbox_theta>
			<x1>423</x1>
			<y1>221</y1>
			<x2>423</x2>
			<y2>191</y2>
			<x3>434</x3>
			<y3>191</y3>
			<x4>434</x4>
			<y4>221</y4>
		</rotated_bndbox>
		<segm>
			<point-1>434,220</point-1>
			<point-2>434,213</point-2>
			<point-3>434,205</point-3>
			<point-4>433,197</point-4>
			<point-5>430,192</point-5>
			<point-6>425,191</point-6>
			<point-7>423,195</point-7>
			<point-8>423,204</point-8>
			<point-9>423,211</point-9>
			<point-10>426,219</point-10>
			<point-11>430,221</point-11>
		</segm>
	</object>
	<object>
		<name>ship</name>
		<pose>Unspecified</pose>
		<truncated>0</truncated>
		<difficult>0</difficult>
		<bndbox>
			<xmin>447</xmin>
			<ymin>51</ymin>
			<xmax>454</xmax>
			<ymax>70</ymax>
			<bbox_w>7</bbox_w>
			<bbox_h>19</bbox_h>
		</bndbox>
		<rotated_bndbox>
			<rotated_bbox_cx>450</rotated_bbox_cx>
			<rotated_bbox_cy>60</rotated_bbox_cy>
			<rotated_bbox_w>7</rotated_bbox_w>
			<rotated_bbox_h>19</rotated_bbox_h>
			<rotated_bbox_theta>0.0</rotated_bbox_theta>
			<x1>447</x1>
			<y1>70</y1>
			<x2>447</x2>
			<y2>51</y2>
			<x3>454</x3>
			<y3>51</y3>
			<x4>454</x4>
			<y4>70</y4>
		</rotated_bndbox>
		<segm>
			<point-1>452,70</point-1>
			<point-2>454,65</point-2>
			<point-3>454,57</point-3>
			<point-4>453,52</point-4>
			<point-5>448,51</point-5>
			<point-6>447,57</point-6>
			<point-7>447,64</point-7>
			<point-8>447,69</point-8>
		</segm>
	</object>
	<object>
		<name>ship</name>
		<pose>Unspecified</pose>
		<truncated>0</truncated>
		<difficult>0</difficult>
		<bndbox>
			<xmin>476</xmin>
			<ymin>140</ymin>
			<xmax>485</xmax>
			<ymax>159</ymax>
			<bbox_w>9</bbox_w>
			<bbox_h>19</bbox_h>
		</bndbox>
		<rotated_bndbox>
			<rotated_bbox_cx>480</rotated_bbox_cx>
			<rotated_bbox_cy>149</rotated_bbox_cy>
			<rotated_bbox_w>19</rotated_bbox_w>
			<rotated_bbox_h>9</rotated_bbox_h>
			<rotated_bbox_theta>90.0</rotated_bbox_theta>
			<x1>476</x1>
			<y1>140</y1>
			<x2>485</x2>
			<y2>140</y2>
			<x3>485</x3>
			<y3>159</y3>
			<x4>476</x4>
			<y4>159</y4>
		</rotated_bndbox>
		<segm>
			<point-1>483,159</point-1>
			<point-2>485,153</point-2>
			<point-3>485,146</point-3>
			<point-4>482,140</point-4>
			<point-5>478,140</point-5>
			<point-6>476,141</point-6>
			<point-7>476,148</point-7>
			<point-8>476,153</point-8>
			<point-9>478,159</point-9>
		</segm>
	</object>
</annotation>